mcp_aktools/__init__.py
mcp_aktools/__main__.py
mcp_aktools/cache.py
mcp_aktools/prompts.py
mcp_aktools/resources.py
mcp_aktools/server.py
mcp_aktools/shared/__init__.py
mcp_aktools/shared/constants.py
mcp_aktools/shared/fields.py
mcp_aktools/shared/indicators.py
mcp_aktools/shared/utils.py
mcp_aktools/tools/__init__.py
mcp_aktools/tools/analysis.py
mcp_aktools/tools/crypto.py
mcp_aktools/tools/forex.py
mcp_aktools/tools/funds.py
mcp_aktools/tools/futures.py
mcp_aktools/tools/macro.py
mcp_aktools/tools/market.py
mcp_aktools/tools/portfolio.py
mcp_aktools/tools/precious_metals.py
mcp_aktools/tools/stocks.py
aktools_pro-0.5.3.dist-info/METADATA
aktools_pro-0.5.3.dist-info/WHEEL
aktools_pro-0.5.3.dist-info/entry_points.txt
aktools_pro-0.5.3.dist-info/licenses/LICENSE
aktools_pro-0.5.3.dist-info/RECORD
